{
  "Search": [
    {
      "Title": "Pirates of the Caribbean: At World's End",
      "Year": "2007",
      "imdbID": "tt0449088",
      "Type": "movie",
      "Poster": "https://m.media-amazon.com/images/M/MV5BMjIyNjkxNzEyMl5BMl5BanBnXkFtZTYwMjc3MDE3._V1_SX300.jpg"
    },
    {
      "Title": "This Is the End",
      "Year": "2013",
      "imdbID": "tt1245492",
      "Type": "movie",
      "Poster": "https://m.media-amazon.com/images/M/MV5BMTQxODE3NjM1Ml5BMl5BanBnXkFtZTcwMzkzNjc4OA@@._V1_SX300.jpg"
    },
    {
      "Title": "The World's End",
      "Year": "2013",
      "imdbID": "tt1213663",
      "Type": "movie",
      "Poster": "https://m.media-amazon.com/images/M/MV5BNzA1MTk1MzY0OV5BMl5BanBnXkFtZTgwNjkzNTUwMDE@._V1_SX300.jpg"
    },
    {
      "Title": "The End of the F***ing World",
      "Year": "2017–2019",
      "imdbID": "tt6257970",
      "Type": "series",
      "Poster": "https://m.media-amazon.com/images/M/MV5BN2ZhNmQ2MjQtMmQzMi00YjE5LTlkMWMtMjk5YzIxMjk2NDc2XkEyXkFqcGdeQXVyMTkxNjUyNQ@@._V1_SX300.jpg"
    },
    {
      "Title": "Seeking a Friend for the End of the World",
      "Year": "2012",
      "imdbID": "tt1307068",
      "Type": "movie",
      "Poster": "https://m.media-amazon.com/images/M/MV5BMTk4MDQ1NzE3N15BMl5BanBnXkFtZTcwMjA0MDkzNw@@._V1_SX300.jpg"
    },
    {
      "Title": "House at the End of the Street",
      "Year": "2012",
      "imdbID": "tt1582507",
      "Type": "movie",
      "Poster": "https://m.media-amazon.com/images/M/MV5BMjIxNTUwNTU4N15BMl5BanBnXkFtZTcwNTE0MTI3Nw@@._V1_SX300.jpg"
    },
    {
      "Title": "Neon Genesis Evangelion: The End of Evangelion",
      "Year": "1997",
      "imdbID": "tt0169858",
      "Type": "movie",
      "Poster": "https://m.media-amazon.com/images/M/MV5BMjU0MzQwMmMtMWU3OS00MDc0LWIzOTItZmE1MjZlYmExMGJiXkEyXkFqcGdeQXVyNzI1NzMxNzM@._V1_SX300.jpg"
    },
    {
      "Title": "John Dies at the End",
      "Year": "2012",
      "imdbID": "tt1783732",
      "Type": "movie",
      "Poster": "https://m.media-amazon.com/images/M/MV5BMTUyNzIyNzc0MV5BMl5BanBnXkFtZTcwOTM5ODg1OA@@._V1_SX300.jpg"
    },
    {
      "Title": "The End of the Tour",
      "Year": "2015",
      "imdbID": "tt3416744",
      "Type": "movie",
      "Poster": "https://m.media-amazon.com/images/M/MV5BMTUwODU3NjQxNF5BMl5BanBnXkFtZTgwODE2NTE4NTE@._V1_SX300.jpg"
    },
    {
      "Title": "It's Only the End of the World",
      "Year": "2016",
      "imdbID": "tt4645368",
      "Type": "movie",
      "Poster": "https://m.media-amazon.com/images/M/MV5BODJiZWMyMjQtYjM4Zi00MzVjLWEzZGMtZThlNGJlMmRkYjYxXkEyXkFqcGdeQXVyNDkzNTM2ODg@._V1_SX300.jpg"
    }
  ]
}
